image.py
study.py
rebadicom-0.0.1.dist-info/LICENSE
rebadicom-0.0.1.dist-info/METADATA
rebadicom-0.0.1.dist-info/WHEEL
rebadicom-0.0.1.dist-info/top_level.txt
rebadicom-0.0.1.dist-info/RECORD
