Metadata-Version: 2.1
Name: rebadicom
Version: 0.0.1
Summary: UNKNOWN
Home-page: UNKNOWN
Author: UNKNOWN
Author-email: UNKNOWN
License: UNKNOWN
Platform: UNKNOWN
Requires-Dist: cycler (==0.11.0)
Requires-Dist: flake8 (==4.0.1)
Requires-Dist: fonttools (==4.29.1)
Requires-Dist: importlib-metadata (==4.2.0)
Requires-Dist: kiwisolver (==1.3.2)
Requires-Dist: matplotlib (==3.5.1)
Requires-Dist: mccabe (==0.6.1)
Requires-Dist: numpy (==1.21.5)
Requires-Dist: packaging (==21.3)
Requires-Dist: Pillow (==9.0.1)
Requires-Dist: pycodestyle (==2.8.0)
Requires-Dist: pydicom (==2.2.2)
Requires-Dist: pyflakes (==2.4.0)
Requires-Dist: pyparsing (==3.0.7)
Requires-Dist: python-dateutil (==2.8.2)
Requires-Dist: six (==1.16.0)
Requires-Dist: typing-extensions (==4.1.1)
Requires-Dist: zipp (==3.7.0)
